Creating_Own_Package/__init__.py
Creating_Own_Package/maths.py
creating_own_package-0.1.0.dist-info/METADATA
creating_own_package-0.1.0.dist-info/WHEEL
creating_own_package-0.1.0.dist-info/top_level.txt
creating_own_package-0.1.0.dist-info/RECORD
