Metadata-Version: 2.4
Name: creating_own_package
Version: 0.1.0
Summary: A simple math utility package
Author-email: Anshu Yadav <anshu@dianapps.com>
License: MLT
Project-URL: Homepage, https://github.com/anshuDianapps/Creating_Own_Package
Classifier: Programming Language :: Python :: 3
Classifier: License :: OSI Approved :: MIT License
Classifier: Operating System :: OS Independent
Requires-Python: >=3.7
